{"file": "\"\"\"Pair matcher: flags candidate rows whose two amounts are within 5% of each other.\"\"\"\n\nTOOL = {\n    \"name\": \"amount_pair_matcher\",\n    \"description\": \"Flags rows where amount and amount_b differ by no more than 5% of the larger.\",\n    \"args_schema\": {\"type\": \"object\", \"properties\": {\"rows\": {\"type\": \"array\"}},\n                    \"required\": [\"rows\"]},\n}\nSELF_TEST = {\n    \"args\": {\"rows\": [{\"amount\": 100.0, \"amount_b\": 103.0},\n                      {\"amount\": 100.0, \"amount_b\": 200.0}]},\n    \"expect_keys\": [\"findings\"],\n}\n\n\ndef run(args: dict) -> dict:\n    findings = []\n    for row in args.get(\"rows\", []):\n        try:\n            a = float(row.get(\"amount\", 0))\n            b = float(row.get(\"amount_b\", 0))\n        except (TypeError, ValueError):\n            continue\n        hi = max(abs(a), abs(b))\n        if hi and abs(a - b) <= 0.05 * hi:\n            findings.append(row)\n    return {\"findings\": findings, \"checked\": len(args.get(\"rows\", []))}\n"}